bapsflib/__init__.py
bapsflib/_hdf/__init__.py
bapsflib/_hdf/maps/__init__.py
bapsflib/_hdf/maps/mapper.py
bapsflib/_hdf/maps/templates.py
bapsflib/_hdf/maps/controls/__init__.py
bapsflib/_hdf/maps/controls/bmotion.py
bapsflib/_hdf/maps/controls/map_controls.py
bapsflib/_hdf/maps/controls/n5700ps.py
bapsflib/_hdf/maps/controls/nixyz.py
bapsflib/_hdf/maps/controls/nixz.py
bapsflib/_hdf/maps/controls/parsers.py
bapsflib/_hdf/maps/controls/sixk.py
bapsflib/_hdf/maps/controls/templates.py
bapsflib/_hdf/maps/controls/types.py
bapsflib/_hdf/maps/controls/waveform.py
bapsflib/_hdf/maps/controls/tests/__init__.py
bapsflib/_hdf/maps/controls/tests/common.py
bapsflib/_hdf/maps/controls/tests/fauxbmotion.py
bapsflib/_hdf/maps/controls/tests/fauxn5700ps.py
bapsflib/_hdf/maps/controls/tests/fauxnixyz.py
bapsflib/_hdf/maps/controls/tests/fauxnixz.py
bapsflib/_hdf/maps/controls/tests/fauxsixk.py
bapsflib/_hdf/maps/controls/tests/fauxwaveform.py
bapsflib/_hdf/maps/controls/tests/test_bmotion.py
bapsflib/_hdf/maps/controls/tests/test_map_controls.py
bapsflib/_hdf/maps/controls/tests/test_n5700ps.py
bapsflib/_hdf/maps/controls/tests/test_nixyz.py
bapsflib/_hdf/maps/controls/tests/test_nixz.py
bapsflib/_hdf/maps/controls/tests/test_parsers.py
bapsflib/_hdf/maps/controls/tests/test_sixk.py
bapsflib/_hdf/maps/controls/tests/test_templates.py
bapsflib/_hdf/maps/controls/tests/test_types.py
bapsflib/_hdf/maps/controls/tests/test_waveform.py
bapsflib/_hdf/maps/digitizers/__init__.py
bapsflib/_hdf/maps/digitizers/map_digis.py
bapsflib/_hdf/maps/digitizers/sis3301.py
bapsflib/_hdf/maps/digitizers/siscrate.py
bapsflib/_hdf/maps/digitizers/templates.py
bapsflib/_hdf/maps/digitizers/tests/__init__.py
bapsflib/_hdf/maps/digitizers/tests/common.py
bapsflib/_hdf/maps/digitizers/tests/fauxsis3301.py
bapsflib/_hdf/maps/digitizers/tests/fauxsiscrate.py
bapsflib/_hdf/maps/digitizers/tests/test_map_digis.py
bapsflib/_hdf/maps/digitizers/tests/test_sis3301.py
bapsflib-2025.6.0.dist-info/licenses/LICENSES/LICENSE.txt
bapsflib-2025.6.0.dist-info/METADATA
bapsflib-2025.6.0.dist-info/WHEEL
bapsflib-2025.6.0.dist-info/top_level.txt
bapsflib-2025.6.0.dist-info/RECORD
