Metadata-Version: 2.4
Name: bapsflib
Version: 2025.6.0
Summary: A toolkit for handling data collected at BaPSF
Home-page: https://github.com/BaPSF/bapsflib
Download-URL: https://pypi.org/project/bapsflib/
Author: Basic Plasma Science Facility
Maintainer: Erik T. Everson
Maintainer-email: eeverson@physics.ucla.edu
License: 3-clause BSD
Project-URL: BaPSF, http://plasma.physics.ucla.edu/
Project-URL: Documentation, https://bapsflib.readthedocs.io/en/latest/
Project-URL: GitHub, https://github.com/BaPSF/bapsflib
Keywords: bapsf,HDF5,lapd,physics,plasma,plasma physics,science
Classifier: Intended Audience :: Developers
Classifier: Intended Audience :: Education
Classifier: Intended Audience :: Science/Research
Classifier: License :: OSI Approved :: BSD License
Classifier: Natural Language :: English
Classifier: Operating System :: MacOS
Classifier: Operating System :: Microsoft :: Windows
Classifier: Operating System :: POSIX :: Linux
Classifier: Programming Language :: Python :: 3
Classifier: Topic :: Education
Classifier: Topic :: Scientific/Engineering
Classifier: Topic :: Scientific/Engineering :: Physics
Classifier: Topic :: Software Development
Classifier: Topic :: Software Development :: Libraries :: Python Modules
Requires-Python: >=3.9
License-File: LICENSES/LICENSE.txt
Requires-Dist: astropy>=4.3.1
Requires-Dist: bapsf_motion>=0.2
Requires-Dist: h5py>=3.0
Requires-Dist: numpy>=1.20
Requires-Dist: scipy>=0.19
Provides-Extra: extras
Requires-Dist: black==24.3.0; extra == "extras"
Requires-Dist: codespell; extra == "extras"
Requires-Dist: isort; extra == "extras"
Provides-Extra: tests
Requires-Dist: codecov>=2.0.15; extra == "tests"
Requires-Dist: coverage[toml]>=4.5.1; extra == "tests"
Provides-Extra: docs
Requires-Dist: numpydoc>=1.6; extra == "docs"
Requires-Dist: packaging; extra == "docs"
Requires-Dist: sphinx>=3.2.0; extra == "docs"
Requires-Dist: sphinx-automodapi>=0.13; extra == "docs"
Requires-Dist: sphinx-changelog; extra == "docs"
Requires-Dist: sphinx-gallery; extra == "docs"
Requires-Dist: sphinx-hoverxref>=1.3; extra == "docs"
Requires-Dist: sphinx_rtd_theme; extra == "docs"
Requires-Dist: towncrier==22.8.0; extra == "docs"
Provides-Extra: developer
Requires-Dist: numpydoc>=1.6; extra == "developer"
Requires-Dist: packaging; extra == "developer"
Requires-Dist: sphinx>=3.2.0; extra == "developer"
Requires-Dist: sphinx-automodapi>=0.13; extra == "developer"
Requires-Dist: sphinx-changelog; extra == "developer"
Requires-Dist: sphinx-gallery; extra == "developer"
Requires-Dist: sphinx-hoverxref>=1.3; extra == "developer"
Requires-Dist: sphinx_rtd_theme; extra == "developer"
Requires-Dist: towncrier==22.8.0; extra == "developer"
Requires-Dist: black==24.3.0; extra == "developer"
Requires-Dist: codespell; extra == "developer"
Requires-Dist: isort; extra == "developer"
Requires-Dist: codecov>=2.0.15; extra == "developer"
Requires-Dist: coverage[toml]>=4.5.1; extra == "developer"
Dynamic: download-url
Dynamic: license-file
